LICENSE
MANIFEST.in
README.rst
setup.py
gax_google_pubsub_v1.egg-info/PKG-INFO
gax_google_pubsub_v1.egg-info/SOURCES.txt
gax_google_pubsub_v1.egg-info/dependency_links.txt
gax_google_pubsub_v1.egg-info/namespace_packages.txt
gax_google_pubsub_v1.egg-info/requires.txt
gax_google_pubsub_v1.egg-info/top_level.txt
google/__init__.py
google/__init__.pyc
google/cloud/__init__.py
google/cloud/__init__.pyc
google/cloud/pubsub/__init__.py
google/cloud/pubsub/__init__.pyc
google/cloud/pubsub/v1/__init__.py
google/cloud/pubsub/v1/publisher_api.py
google/cloud/pubsub/v1/publisher_client_config.json
google/cloud/pubsub/v1/subscriber_api.py
google/cloud/pubsub/v1/subscriber_client_config.json